  {
    "preprocess": [true],
    "s2_levels": ["l1c", "l2a"],
    "sel_sensor": ["s2a", "s2b"],
    "online": [true],
      "order_lta": [true],
      "downloader": ["builtin"],
    "overwrite_safe": [false],
    "rm_safe": ["no"],
    "max_cloud_safe": [100],
    "step_atmcorr": ["l2a"],
    "sen2cor_use_dem": [null],
    "sen2cor_gipp": [null],
    "timewindow": [null],
    "timeperiod": ["full"],
    "extent": [null],
    "s2tiles_selected": [null],
    "s2orbits_selected": [null],
    "list_prods": ["SCL", "BOA"],
    "list_indices": ["NDMI", "NDVI", "NDWI", "NBR", "SAVI", "EVI", "MSI", "TCARI-OSAVI"],
    "list_rgb": ["RGB432B"],
    "rgb_ranges": [[0, 2500]],
    "index_source": ["BOA"],
    "mask_type": [null],
    "max_mask": [100],
    "mask_smooth": [0],
    "mask_buffer": [0],
    "clip_on_extent": [true],
    "extent_as_mask": [true],
    "extent_name": [null],
    "reference_path": [null],
    "res": [null],
    "res_s2": ["10m"],
    "unit": ["Meter"],
    "proj": [null],
    "resampling": ["near"],
    "resampling_scl": ["near"],
    "outformat": ["GTiff"],
    "rgb_outformat": ["GTiff"],
    "index_datatype": ["Float32"],
    "compression": ["DEFLATE"],
    "rgb_compression": ["DEFLATE"],
    "overwrite": [false],
    "path_l1c": ["./l1c"],
    "path_l2a": ["./l2a"],  
    "path_tiles": [null],
    "path_merged": [null],
    "path_out": ["./out"],
    "path_rgb": [""],
    "path_indices": ["./indices"],
    "path_subdirs": [true],
    "thumbnails": [false],
    "log": [null],
    "parallel": [true],
    "processing_order": ["mixed"],
    "pkg_version": ["1.3.0"],
    "server": ["gcloud"]
  } 
